starbars/__init__.py
starbars/_utils.py
starbars-3.1.1.dist-info/LICENSE
starbars-3.1.1.dist-info/WHEEL
starbars-3.1.1.dist-info/METADATA
starbars-3.1.1.dist-info/RECORD
