Metadata-Version: 2.1
Name: starbars
Version: 3.1.1
Summary: Visualize statistical significance on existing Matplotlib plots by adding
Author-email: Elide Brunelli <elide.98@gmail.com>
Classifier: License :: OSI Approved :: MIT License
Requires-Dist: matplotlib~=3.9
Requires-Dist: starbars[examples] ; extra == "docs"
Requires-Dist: sphinx-book-theme~=1.1 ; extra == "docs"
Requires-Dist: sphinx~=7.0 ; extra == "docs"
Requires-Dist: pandas~=2.2 ; extra == "examples"
Requires-Dist: seaborn~=0.13 ; extra == "examples"
Requires-Dist: scipy~=1.14 ; extra == "examples"
Requires-Dist: pytest ; extra == "test"
Requires-Dist: pytest-cov ; extra == "test"
Requires-Dist: pandas~=2.2 ; extra == "test"
Requires-Dist: seaborn~=0.13 ; extra == "test"
Requires-Dist: scipy ; extra == "test"
Project-URL: Home, https://github.com/elide-b/starbars
Provides-Extra: docs
Provides-Extra: examples
Provides-Extra: test
